stlist/__init__.py
stlist-1.0.0.dist-info/AUTHORS
stlist-1.0.0.dist-info/LICENSE
stlist-1.0.0.dist-info/METADATA
stlist-1.0.0.dist-info/WHEEL
stlist-1.0.0.dist-info/top_level.txt
stlist-1.0.0.dist-info/RECORD
