Metadata-Version: 2.1
Name: stlist
Version: 1.0.0
Summary: stlist is a library for reading/writing binary plists.
Home-page: https://github.com/FoleyDiver/stlist
Author: Steve Foley
Author-email: sfoley1988@gmail.com
License: BSD
Download-URL: https://github.com/FoleyDiver/stlist/archive/v1.0.0.tar.gz
Platform: UNKNOWN
Classifier: Development Status :: 5 - Production/Stable
Classifier: Intended Audience :: Developers
Classifier: License :: OSI Approved :: BSD License
Classifier: Operating System :: OS Independent
Classifier: Programming Language :: Python
Classifier: Topic :: Software Development :: Libraries :: Python Modules
Classifier: Topic :: Text Processing :: Markup
